fjagepy/AgentID.py
fjagepy/Connector.py
fjagepy/Gateway.py
fjagepy/JSONMessage.py
fjagepy/Message.py
fjagepy/Performative.py
fjagepy/Services.py
fjagepy/TCPConnector.py
fjagepy/Utils.py
fjagepy/__init__.py
fjagepy-2.0.0.dist-info/licenses/LICENSE
fjagepy-2.0.0.dist-info/METADATA
fjagepy-2.0.0.dist-info/WHEEL
fjagepy-2.0.0.dist-info/top_level.txt
fjagepy-2.0.0.dist-info/RECORD
