Metadata-Version: 2.4
Name: fjagepy
Version: 2.0.0
Summary: fjage Gateway in Python
Author-email: Chinmay Pendharkar <chinmay@subnero.com>
Requires-Python: >=3.9
License-File: LICENSE
Provides-Extra: dev
Requires-Dist: pytest==8.3.5; extra == "dev"
Requires-Dist: numpy==2.3.0; extra == "dev"
Provides-Extra: docs
Requires-Dist: sphinx==8.2.3; extra == "docs"
Requires-Dist: sphinx-rtd-theme==3.0.2; extra == "docs"
Requires-Dist: myst-parser==4.0.1; extra == "docs"
Dynamic: license-file
